backloop/__init__.py
backloop/comment_service.py
backloop/config.py
backloop/event_manager.py
backloop/file_watcher.py
backloop/git_service.py
backloop/mock_data.py
backloop/models.py
backloop/py.typed
backloop/review_session.py
backloop/server.py
backloop/api/__init__.py
backloop/api/responses.py
backloop/api/review_router.py
backloop/mcp/__init__.py
backloop/mcp/server.py
backloop/services/mcp_service.py
backloop/services/review_service.py
backloop/static/favicon.ico
backloop/static/favicon.svg
backloop/static/css/buttons.css
backloop/static/css/components.css
backloop/static/css/diff.css
backloop/static/css/main.css
backloop/static/js/api.js
backloop/static/js/comments.js
backloop/static/js/diff-viewer.js
backloop/static/js/file-editor.js
backloop/static/js/main.js
backloop/static/js/websocket-client.js
backloop/static/templates/review.html
backloop/utils/__init__.py
backloop/utils/common.py
backloop/utils/state_dir.py
backloop-0.3.1.dist-info/METADATA
backloop-0.3.1.dist-info/WHEEL
backloop-0.3.1.dist-info/entry_points.txt
backloop-0.3.1.dist-info/licenses/LICENSE
backloop-0.3.1.dist-info/RECORD
