Metadata-Version: 2.4
Name: backloop
Version: 0.3.1
Summary: A web-based git diff viewer and review tool with MCP server integration
Author-email: Benno Evers <benno@bmevers.de>
License-Expression: AGPL-3.0
License-File: LICENSE
Keywords: code-review,diff,fastapi,git,mcp,review
Classifier: Development Status :: 3 - Alpha
Classifier: Intended Audience :: Developers
Classifier: License :: OSI Approved :: GNU Affero General Public License v3
Classifier: Programming Language :: Python :: 3
Classifier: Programming Language :: Python :: 3.13
Classifier: Topic :: Software Development :: Quality Assurance
Classifier: Topic :: Software Development :: Version Control :: Git
Requires-Python: >=3.13
Requires-Dist: fastapi>=0.115.6
Requires-Dist: mcp>=1.2.0
Requires-Dist: nest-asyncio>=1.6.0
Requires-Dist: pathspec>=0.12.1
Requires-Dist: pydantic>=2.11.7
Requires-Dist: uvicorn[standard]>=0.34.0
Requires-Dist: watchdog>=6.0.0
